skres/__init__.py
scikit_res-0.1.1.dist-info/LICENSE
scikit_res-0.1.1.dist-info/METADATA
scikit_res-0.1.1.dist-info/WHEEL
scikit_res-0.1.1.dist-info/RECORD
