Metadata-Version: 2.1
Name: scikit-res
Version: 0.1.1
Summary: Very Basic package to store results of ML models
Author: AlexandreGazagnes
Author-email: alex@gazagnes.net
Requires-Python: ==3.10.12
Classifier: Programming Language :: Python :: 3
Requires-Dist: pandas (>=2.1.4,<3.0.0)
Requires-Dist: scikit-learn (>=1.4.0,<2.0.0)
